ObservabilityAPI/__init__.py
ObservabilityAPI/api_client.py
ObservabilityAPI/api_response.py
ObservabilityAPI/configuration.py
ObservabilityAPI/exceptions.py
ObservabilityAPI/py.typed
ObservabilityAPI/rest.py
ObservabilityAPI/api/__init__.py
ObservabilityAPI/api/grafana_api.py
ObservabilityAPI/api/prometheus_api.py
ObservabilityAPI/models/__init__.py
ObservabilityAPI/models/add_exporter_to_host200_response.py
ObservabilityAPI/models/add_exporter_to_host200_response_exporter.py
ObservabilityAPI/models/add_grafana_datasource200_response.py
ObservabilityAPI/models/add_prometheus_target200_response.py
ObservabilityAPI/models/db_phrame_json_store.py
ObservabilityAPI/models/deploy_grafana_dashboards200_response.py
ObservabilityAPI/models/generate_grafana_service_key200_response.py
ObservabilityAPI/models/get_prometheus_targets200_response.py
ObservabilityAPI/models/get_prometheus_targets200_response_targets_inner.py
ObservabilityAPI/models/get_prometheus_targets200_response_targets_inner_ports.py
ObservabilityAPI/models/remove_prometheus_target200_response.py
observabilityapi-1.0.7.dist-info/licenses/LICENSE
observabilityapi-1.0.7.dist-info/METADATA
observabilityapi-1.0.7.dist-info/WHEEL
observabilityapi-1.0.7.dist-info/top_level.txt
observabilityapi-1.0.7.dist-info/RECORD
